<?xml version="1.0" encoding="UTF-8"?>
<?xml-model href="../schema/out/dragon_schema.rng" type="application/xml" schematypens="http://relaxng.org/ns/structure/1.0"?>
<div xmlns="http://www.tei-c.org/ns/1.0"
      type="page"
      n="4r"
      xml:id="p0021">
      
      <ab type="transcription"
            xml:id="p0021_transcription"
            corresp="#p0021_translation">
            
            <lb/>cat vite 
            <choice>
                  <seg type="lucas">mun(er)a.</seg>
                  <orig>muṅa.</orig>
                  <reg>munera.</reg>
            </choice> 
            <choice>
                  <seg type="lucas">V(espers)</seg>
                  <orig>V̇</orig>
                  <reg>Vespers</reg>
            </choice> 
            <choice>
                  <seg type="lucas">Dab(is)</seg>
                  <orig>Daḃ</orig>
                  <reg>Dabis</reg>
                  <!-- not entirely sure about b(is) abbreviation -->
            </choice>
            <lb/>
            <choice>
                  <seg type="lucas">eu(m)</seg>
                  <orig>eu̇</orig>
                  <reg>eum</reg>
            </choice> 
            <choice>
                  <seg type="lucas">i(n)</seg>
                  <orig>ī</orig>
                  <reg>in</reg>
            </choice> 
            <choice>
                  <seg type="lucas">b(e)n(e)dict(i)o(nem)</seg>
                  <orig>bṅdictȯ⋮</orig>
                  <reg>benedictionem</reg>
            </choice> 
            <choice>
                  <seg type="lucas">i(n)</seg>
                  <orig>ī</orig>
                  <reg>in</reg>
            </choice> 
            <choice>
                  <seg type="lucas">s(e)c(u)l(u)m</seg>
                  <orig>scľm</orig>
                  <reg>seculum</reg>
                  <!-- please double check the ľ -->
            </choice> 
            <choice>
                  <seg type="lucas">s(e)c(u)li</seg>
                  <orig>scli</orig>
                  <reg>seculi</reg>
            </choice> ;
            <lb/>
            <choice>
                  <seg type="lucas">Letificab(is)</seg>
                  <orig>Letificaḃ</orig>
                  <reg>Letificabis</reg>
                  <!-- please double check bis -->
            </choice> 
            <choice>
                  <seg type="lucas">eu(m)</seg>
                  <orig>eu̇</orig>
                  <reg>eum</reg>
            </choice> 
            <choice>
                  <seg type="lucas">i(n)</seg>
                  <orig>ī</orig>
                  <reg>in</reg>
            </choice> gaudio 
            <choice>
                  <seg type="lucas">cu(n)</seg>
                  <orig>cu̇</orig>
                  <reg>cun</reg>
            </choice>
            <lb/>
            <choice>
                  <seg type="lucas">DE(us)</seg>
                  <orig>DE</orig>
                  <reg>DEus</reg>
                  <!-- i don't know the unicode for (us) -->
            </choice> 
            <choice>
                  <seg type="lucas">q(u)i</seg>
                  <orig>q͘i</orig>
                  <reg>qui</reg>
            </choice>         
            <choice>
                  <seg type="lucas">Or(aci)o</seg>
                  <orig>Oṙo</orig>
                  <reg>Oracio</reg>
                  <!-- please double check -->
            </choice>         vultu tuo ;
            <lb/>
            <choice>
                  <seg type="lucas">ge(n)tiu(m)</seg>
                  <orig>gėtiu̇</orig>
                  <reg>gentium</reg>
            </choice> 
            <choice>
                  <seg type="lucas">m(u)ltitudine(m)</seg>
                  <orig>ml̇titudinė</orig>
                  <reg>multitudinem</reg>
                  <!-- the dot above the l can't really be seen -->
            </choice> mi
            <lb break="no"/>ra 
            <choice>
                  <seg type="lucas">b(ea)ti</seg>
                  <orig>ḃti</orig>
                  <reg>beati</reg>
            </choice> 
            <choice>
                  <seg type="lucas">Vi(n)ce(n)tii</seg>
                  <orig>Vīcėtii</orig>
                  <reg>Vincentii</reg>
            </choice> 
            <choice>
                  <seg type="lucas">(con)</seg>
                  <orig/>
                  <reg>con</reg>
                  <!-- CON! -->
            </choice>
            <choice>
                  <seg type="lucas">fesso(r)is</seg>
                  <orig>fessȯis</orig>
                  <reg>fessoris</reg>
            </choice> tui
            <lb/>
            <choice>
                  <seg type="lucas">p(re)dicac(i)o(n)e</seg>
                  <orig>pdicacoe</orig>
                  <reg>predicacione</reg>
                  <!-- pre? -->
            </choice> ad 
            <choice>
                  <seg type="lucas">ag(ni)t(i)o(nem)</seg>
                  <orig>aġtȯ⋮</orig>
                  <reg>agnitionem</reg>
            </choice> tui 
            <lb/>
            <choice>
                  <seg type="lucas">no(min)is</seg>
                  <orig>nōis</orig>
                  <reg>nominis</reg>
            </choice> 
            <choice>
                  <seg type="lucas">ve(n)ire</seg>
                  <orig>vēire</orig>
                  <reg>venire</reg>
            </choice> 
            <choice>
                  <seg type="lucas">t(ri)buisti</seg>
                  <orig>t͘buisti</orig>
                  <reg>tribuisti</reg>
            </choice> : 
            <choice>
                  <seg type="lucas">pr(est)a</seg>
                  <orig>pr̄a</orig>
                  <reg>presta</reg>
            </choice>
            <lb/>
            <choice>
                  <seg type="lucas">q(uesumu)s.</seg>
                  <orig>q̄s.</orig>
                  <reg>quesumus.</reg>
            </choice> ut 
            <choice>
                  <seg type="lucas">que(m)</seg>
                  <orig>quē</orig>
                  <reg>quem</reg>
            </choice> 
            <choice>
                  <seg type="lucas">ve(n)tu(rum)</seg>
                  <orig>vētuꝝ</orig>
                  <reg>venturum</reg>
            </choice> 
            <choice>
                  <seg type="lucas">iudice(m)</seg>
                  <orig>iudicē</orig>
                  <reg>iudicem</reg>
            </choice>
            <lb/>
            <choice>
                  <seg type="lucas">nu(n)ciavit</seg>
                  <orig>nūciavit</orig>
                  <reg>nunciavit</reg>
            </choice> 
            <choice>
                  <seg type="lucas">i(n)</seg>
                  <orig>ī</orig>
                  <reg>in</reg>
            </choice> 
            <choice>
                  <seg type="lucas">t(er)ris;</seg>
                  <orig>ṫris;</orig>
                  <reg>terris;</reg>
            </choice> 
            <choice>
                  <seg type="lucas">p(re)miato</seg>
                  <orig>p̄miato</orig>
                  <reg>premiato</reg>
            </choice>
            <lb break="no"/>
            <choice>
                  <seg type="lucas">re(m)</seg>
                  <orig>rē</orig>
                  <reg>rem</reg>
            </choice> 
            <choice>
                  <seg type="lucas">h(abe)re</seg>
                  <orig>hr̄e</orig>
                  <reg>habere</reg>
            </choice> 
            <choice>
                  <seg type="lucas">me(re)am(ur)</seg>
                  <orig>mėam݃</orig>
                  <reg>mereamur</reg>
            </choice> 
            <choice>
                  <seg type="lucas">i(n)</seg>
                  <orig>ī</orig>
                  <reg>in</reg>
            </choice> 
            <choice>
                  <seg type="lucas">cel(is).</seg>
                  <orig>cel͘.</orig>
                  <reg>celis.</reg>
            </choice> 
            <choice>
                  <seg type="lucas">(Christu)m.</seg>
                  <orig>m.</orig>
                  <reg>Christum.</reg>
                  <!-- not sure about this one -->
            </choice> 
            <lb/>
            <choice>
                  <seg type="lucas">An(tiphon).</seg>
                  <orig>An̈.</orig>
                  <reg>Antiphon.</reg>
            </choice> Cristi pia 
            <choice>
                  <seg type="lucas">gr(ati)a</seg>
                  <orig>gr̄a</orig>
                  <reg>gratia</reg>
            </choice> 
            <choice>
                  <seg type="lucas">s(an)c(t)os</seg>
                  <orig>scōs</orig>
                  <reg>sanctos</reg>
            </choice> 
            <lb/>
            <choice>
                  <seg type="lucas">s(u)bli(m)avit</seg>
                  <orig>sḃlīavit</orig>
                  <reg>sublimavit</reg>
            </choice> quos 
            <choice>
                  <seg type="lucas">p(at)ris</seg>
                  <orig>pr̄is</orig>
                  <reg>patris</reg>
            </choice> 
            <choice>
                  <seg type="lucas">D(omi)ni</seg>
                  <orig>Dṅi</orig>
                  <reg>Domini</reg>
            </choice>
            <lb break="no"/>ci ordo 
            <choice>
                  <seg type="lucas">p(ro)pagavit</seg>
                  <orig>ꝓpagavit</orig>
                  <reg>propagavit</reg>
            </choice> nos eo
            <lb break="no"/>
            <choice>
                  <seg type="lucas">(rum) </seg>
                  <orig> ꝝ</orig>
                  <reg>rum </reg>
            </choice> 
            <choice>
                  <seg type="lucas">m(er)itis</seg>
                  <orig>ṁitis</orig>
                  <reg>meritis</reg>
            </choice> 
            <choice>
                  <seg type="lucas">petim(us)</seg>
                  <orig>petimꝰ</orig>
                  <reg>petimus</reg>
            </choice> iuvari 
            
            
      </ab>
      
      <ab type="translation"
            xml:id="p0021_translation"
            corresp="#p0021_transcription"/>
      
</div>
