<?xml version="1.0" encoding="UTF-8"?>
<?xml-model href="../schema/out/dragon_schema.rng" type="application/xml" schematypens="http://relaxng.org/ns/structure/1.0"?>
<div xmlns="http://www.tei-c.org/ns/1.0"
     type="page"
     n="51v"
     xml:id="p0118">

   <ab type="transcription"
       xml:id="p0118_transcription"
       corresp="#p0118_translation">

      <lb/>
	     <choice>
		       <seg type="lucas">sic(ut)</seg>
		       <orig>sic̄</orig>
		       <reg>sicut</reg>
	     </choice> dixit. Infra 
	<choice>
		       <seg type="lucas">pe(n)th(?)co.</seg>
		       <orig>pētḣco.</orig>
		       <reg>penth?co.</reg>
	     </choice>
      <lb/>
	     <choice>
		       <seg type="lucas">Sp(iritu)m</seg>
		       <orig>Sp̄m</orig>
		       <reg>Spiritum</reg>
	     </choice> misit 
	<choice>
		       <seg type="lucas">sic(ut)</seg>
		       <orig>sic̄</orig>
		       <reg>sicut</reg>
	     </choice> dixit. Ad
<lb/>
	     <choice>
		       <seg type="lucas">(com)</seg>
		       <orig>ɔ</orig>
		       <reg>com</reg>
	     </choice>
	     <choice>
		       <seg type="lucas">pl(etorium)</seg>
		       <orig>pl͘</orig>
		       <reg>pletorium</reg>
	     </choice>         Ave maria. 
	<choice>
		       <seg type="lucas">Co(n)v(er)</seg>
		       <orig>Cōv̇</orig>
		       <reg>Conver</reg>
	     </choice>
      <lb break="no"/>te nos 
	<choice>
		       <seg type="lucas">d(eu)s</seg>
		       <orig>ḋs</orig>
		       <reg>deus</reg>
	     </choice> salutaris 
	<choice>
		       <seg type="lucas">n(oste)r.</seg>
		       <orig>nṙ.</orig>
		       <reg>noster.</reg>
	     </choice>
      <lb/>Et 
	<choice>
		       <seg type="lucas">av(er)te</seg>
		       <orig>av̇te</orig>
		       <reg>averte</reg>
	     </choice> 
	     <choice>
		       <seg type="lucas">ira(m)</seg>
		       <orig>irā</orig>
		       <reg>iram</reg>
	     </choice> 
	     <choice>
		       <seg type="lucas">tua(m)</seg>
		       <orig>tuā</orig>
		       <reg>tuam</reg>
	     </choice> a 
	<choice>
		       <seg type="lucas">nob(is).</seg>
		       <orig>noḃ.</orig>
		       <reg>nobis.</reg>
	     </choice> 
	     <choice>
		       <seg type="lucas">D(eu)s</seg>
		       <orig>Ḋs</orig>
		       <reg>Deus</reg>
	     </choice>
      <lb/>
	     <choice>
		       <seg type="lucas">MEme(n)to</seg>
		       <orig>MEmēto</orig>
		       <reg>MEmento</reg>
	     </choice>        
	     <choice>
	           <!-- 0308 not appearing over the P -->
		       <seg type="lucas">Ps(alm)</seg>
		       <orig>Ps</orig>
		       <reg>Psalm</reg>
	     </choice>        
	     <choice>
		       <seg type="lucas">i(n)</seg>
		       <orig>ī</orig>
		       <reg>in</reg>
	     </choice> adiu.
<lb/>
	     <choice>
		       <seg type="lucas">d(omi)ne</seg>
		       <orig>dn̄e</orig>
		       <reg>domine</reg>
	     </choice> david: 
	<choice>
	      <!-- unicode character not assigned -->
		       <seg type="lucas">(et) </seg>
		       <orig> </orig>
		       <reg>et </reg>
	     </choice> 
	     <choice>
		       <seg type="lucas">o(mn)is</seg>
		       <orig>oīs</orig>
		       <reg>omnis</reg>
	     </choice> 
	     <choice>
		       <seg type="lucas">ma(n)</seg>
		       <orig>mā</orig>
		       <reg>man</reg>
	     </choice>
      <lb break="no"/>
	     <choice>
		       <seg type="lucas">suetudi(n)s</seg>
		       <orig>suetudīs</orig>
		       <reg>suetudins</reg>
	     </choice> 
	     <choice>
		       <seg type="lucas">ei(us):</seg>
		       <orig>eiꝰ:</orig>
		       <reg>eius:</reg>
	     </choice> 
	     <choice>
		       <seg type="lucas">Sic(ut)</seg>
		       <orig>Sic̄</orig>
		       <reg>Sicut</reg>
	     </choice> 
	     <choice>
	           <!-- no unicode character for a small riased t -->
		       <seg type="lucas">iurav(it)</seg>
		       <orig>iurav</orig>
		       <reg>iuravit</reg>
	     </choice>
      <lb/>
	     <choice>
		       <seg type="lucas">d(omi)no:</seg>
		       <orig>dn̄o:</orig>
		       <reg>domino:</reg>
	     </choice> 
	     <choice>
		       <seg type="lucas">votu(m)</seg>
		       <orig>votū</orig>
		       <reg>votum</reg>
	     </choice> vovit 
	<choice>
		       <seg type="lucas">d(e)o</seg>
		       <orig>ḋo</orig>
		       <reg>deo</reg>
	     </choice> iacob.
<lb/>Si 
	<choice>
		       <seg type="lucas">i(n)troie(r)o</seg>
		       <orig>ītroiēo</orig>
		       <reg>introiero</reg>
	     </choice> 
	     <choice>
		       <seg type="lucas">i(n)</seg>
		       <orig>ī</orig>
		       <reg>in</reg>
	     </choice> 
	     <choice>
		       <seg type="lucas">tab(er)nac(u)l(um)</seg>
		       <orig>taḃnacl͘⋮</orig>
		       <reg>tabernaculum</reg>
	     </choice> 
	     <choice>
		       <seg type="lucas">dom(us)</seg>
		       <orig>domꝰ</orig>
		       <reg>domus</reg>
	     </choice>
      <lb/>mee: †si† 
	<choice>
		       <seg type="lucas">asce(n)d(er)o</seg>
		       <orig>ascēḋo</orig>
		       <reg>ascendero</reg>
	     </choice> 
	     <choice>
		       <seg type="lucas">i(n)</seg>
		       <orig>ī</orig>
		       <reg>in</reg>
	     </choice> 
	     <choice>
		       <seg type="lucas">l(e)c(tu)m</seg>
		       <orig>lcm̄</orig>
		       <reg>lectum</reg>
	     </choice> strati
<lb/>mei. Si 
	<choice>
		       <seg type="lucas">ded(er)o</seg>
		       <orig>deḋo</orig>
		       <reg>dedero</reg>
	     </choice> 
	     <choice>
	           <!-- check transcription, looks like a p -->
		       <seg type="lucas">so(m)nu(m)</seg>
		       <orig>sōnū</orig>
		       <reg>somnum</reg>
	     </choice> 
	     <choice>
		       <seg type="lucas">ocul(is)</seg>
		       <orig>ocul͘</orig>
		       <reg>oculis</reg>
	     </choice>
      <lb/>meis: 
	<choice>
	      <!-- unicode character not assigned -->
		       <seg type="lucas">(et) </seg>
		       <orig> </orig>
		       <reg>et </reg>
	     </choice> pal 
	<choice>
		       <seg type="lucas">peb(ris)</seg>
		       <orig>peḃ</orig>
		       <reg>pebris</reg>
	     </choice> meis 
	<choice>
		       <seg type="lucas">do(r)</seg>
		       <orig>dȯ</orig>
		       <reg>dor</reg>
	     </choice>
      <lb break="no"/>
	     <choice>
		       <seg type="lucas">mitat(i)o(nem).</seg>
		       <orig>mitatō⋮.</orig>
		       <reg>mitationem.</reg>
	     </choice> Et 
	<choice>
		       <seg type="lucas">req(ui)e(m)</seg>
		       <orig>req̇ē</orig>
		       <reg>requiem</reg>
	     </choice> 
	     <choice>
		       <seg type="lucas">t(em)p(or)ibus</seg>
		       <orig>tꝑibus</orig>
		       <reg>temporibus</reg>
	     </choice>
      <lb/>meis 
	<choice>
		       <seg type="lucas">do(n)ec</seg>
		       <orig>dōec</orig>
		       <reg>donec</reg>
	     </choice> 
	     <choice>
		       <seg type="lucas">i(n)venia(m)</seg>
		       <orig>īveniā</orig>
		       <reg>inveniam</reg>
	     </choice> 
	     <choice>
		       <seg type="lucas">locu(m)</seg>
		       <orig>locū</orig>
		       <reg>locum</reg>
	     </choice> do⸗


</ab>

   <ab type="translation"
       xml:id="p0118_translation"
       corresp="#p0118_transcription"/>

</div>
