<?xml version="1.0" encoding="UTF-8"?>
<?xml-model href="../schema/out/dragon_schema.rng" type="application/xml" schematypens="http://relaxng.org/ns/structure/1.0"?>
<div xmlns="http://www.tei-c.org/ns/1.0"
     type="page"
     n="113r"
     xml:id="p0241">

   <ab type="transcription"
       xml:id="p0241_transcription"
       corresp="#p0241_translation">

      <lb/>
	     <choice>
		       <seg type="lucas">a(m)</seg>
		       <orig>ā</orig>
		       <reg>am</reg>
	     </choice> 
	     <choice>
		       <seg type="lucas">p(ro)nu(n)tiab(un)t.</seg>
		       <orig>pnūtiab̄t.</orig>
		       <reg>pronuntiabunt.</reg>
	     </choice> 
	     <choice>
		       <seg type="lucas">Mag(ni)fice(n)ti</seg>
		       <orig>Maġficēti</orig>
		       <reg>Magnificenti</reg>
	     </choice>
      <lb break="no"/>
	     <choice>
		       <seg type="lucas">a(m)</seg>
		       <orig>ā</orig>
		       <reg>am</reg>
	     </choice> 
	     <choice>
		       <seg type="lucas">gl(ori)e</seg>
		       <orig>gl͘e</orig>
		       <reg>glorie</reg>
	     </choice> 
	     <choice>
		       <seg type="lucas">s(an)c(t)itatis</seg>
		       <orig>sc̄itatis</orig>
		       <reg>sanctitatis</reg>
	     </choice> tue 
	<choice>
	    <seg type="lucas">loq(ue)nt(ur):</seg>
		       <orig>loq̄unt݃ </orig>
		       <reg>loquentur:</reg>
	     </choice>
      <lb/>
	     <choice>
		       <seg type="lucas">(et) </seg>
		       <orig>+ </orig>
		       <reg>et </reg>
	     </choice> mirabilia tua 
	<choice>
		       <seg type="lucas">narrab(un)t.</seg>
		       <orig>narrab̄t.</orig>
		       <reg>narrabunt.</reg>
	     </choice>
      <lb/>Et 
	<choice>
		       <seg type="lucas">v(ir)tute(m)</seg>
		       <orig>v̇tutē</orig>
		       <reg>virtutem</reg>
	     </choice> 
	     <choice>
		       <seg type="lucas">t(er)ribiliu(m)</seg>
		       <orig>ṫribiliū</orig>
		       <reg>terribilium</reg>
	     </choice> 
	     <choice>
		       <seg type="lucas">tuor(um)</seg>
		       <orig>tuoꝝ</orig>
		       <reg>tuorum</reg>
	     </choice>
      <lb/>
	     <choice>
		       <seg type="lucas">dice(n)t:</seg>
		       <orig>dicēt:</orig>
		       <reg>dicent:</reg>
	     </choice> 
	     <choice>
		       <seg type="lucas">(et) </seg>
		       <orig>+ </orig>
		       <reg>et </reg>
	     </choice> 
	     <choice>
		       <seg type="lucas">mag(ni)tudine(m)</seg>
		       <orig>maġtudinē</orig>
		       <reg>magnitudinem</reg>
	     </choice> 
	     <choice>
		       <seg type="lucas">tua(m)</seg>
		       <orig>tuā</orig>
		       <reg>tuam</reg>
	     </choice>
      <lb/>
	     <choice>
		       <seg type="lucas">narrab(un)t.</seg>
		       <orig>narrab̄t.</orig>
		       <reg>narrabunt.</reg>
	     </choice> 
	     <choice>
		       <seg type="lucas">Me(m)oria(m)</seg>
		       <orig>Mēoriā</orig>
		       <reg>Memoriam</reg>
	     </choice> 
	     <choice>
		       <seg type="lucas">(ab)un</seg>
		       <orig>hūn</orig>
	         <!-- this looks like an h not an ab, what's going on here? -->
		       <reg>abun</reg>
	     </choice> 
      <lb break="no"/>
	     <choice>
		       <seg type="lucas">da(n)tie</seg>
		       <orig>dātie</orig>
		       <reg>dantie</reg>
	     </choice> suavitatis tue eruc
<lb break="no"/>
	     <choice>
		       <seg type="lucas">tab(un)t:</seg>
		       <orig>tab̄t:</orig>
		       <reg>tabunt:</reg>
	     </choice> 
	     <choice>
		       <seg type="lucas">(et) </seg>
		       <orig>+ </orig>
		       <reg>et </reg>
	     </choice> iusticia tua exul
<lb break="no"/>
	     <choice>
		       <seg type="lucas">tab(un)t.</seg>
		       <orig>tab̄t.</orig>
		       <reg>tabunt.</reg>
	     </choice> 
	     <choice>
		       <seg type="lucas">Mis(er)ator</seg>
		       <orig>Misȧtor</orig>
		       <reg>Miserator</reg>
	     </choice> 
	     <choice>
		       <seg type="lucas">(et) </seg>
		       <orig>+ </orig>
		       <reg>et </reg>
	     </choice> 
	     <choice>
		       <seg type="lucas">mi(seri)cors</seg>
		       <orig>m̄icors</orig>
		       <reg>misericors</reg>
	     </choice>
      <lb/>
	     <choice>
		       <seg type="lucas">d(omi)n(u)s:</seg>
		       <orig>dn̄s:</orig>
		       <reg>dominus:</reg>
	     </choice> 
	     <choice>
		       <seg type="lucas">patie(n)s</seg>
		       <orig>patiēs</orig>
		       <reg>patiens</reg>
	     </choice> 
	     <choice>
		       <seg type="lucas">(et) </seg>
		       <orig>+ </orig>
		       <reg>et </reg>
	     </choice> 
	     <choice>
		       <seg type="lucas">m(u)ltu(m)</seg>
		       <orig>ml͘tū</orig>
		       <reg>multum</reg>
	     </choice> 
	     <choice>
		       <seg type="lucas">mi(seri)co(r)s</seg>
		       <orig>mīcȯs</orig>
		       <reg>misericors</reg>
	     </choice>
      <lb/>Suavis 
	<choice>
		       <seg type="lucas">d(omi)n(u)s</seg>
		       <orig>dn̄s</orig>
		       <reg>dominus</reg>
	     </choice> 
	     <choice>
		       <seg type="lucas">univ(er)sis:</seg>
		       <orig>univ̇sis:</orig>
		       <reg>universis:</reg>
	     </choice> 
	     <choice>
		       <seg type="lucas">(et)</seg>
		       <orig>+</orig>
		       <reg>et</reg>
	     </choice>
      <lb/>
	     <choice>
		       <seg type="lucas">miserat(i)o(n)es</seg>
		       <orig>miseratōes</orig>
		       <reg>miserationes</reg>
	     </choice> 
	     <choice>
		       <seg type="lucas">ei(us)</seg>
		       <orig>eiꝰ</orig>
		       <reg>eius</reg>
	     </choice> 
	     <choice>
		       <seg type="lucas">s(upe)r</seg>
		       <orig>sr̄</orig>
		       <reg>super</reg>
	     </choice> 
	     <choice>
		       <seg type="lucas">o(mn)ia</seg>
		       <orig>oīa</orig>
		       <reg>omnia</reg>
	     </choice> 
	     <choice>
		       <seg type="lucas">op(er)a</seg>
		       <orig>oꝑa</orig>
		       <reg>opera</reg>
	     </choice>
      <lb/>
	     <choice>
		       <seg type="lucas">ei(us).</seg>
		       <orig>eiꝰ.</orig>
		       <reg>eius.</reg>
	     </choice> 
	     <choice>
		       <seg type="lucas">Co(n)fitea(n)t(ur)</seg>
		       <orig>Cōfiteāt݃</orig>
		       <reg>Confiteantur</reg>
	     </choice> 
	     <choice>
		       <seg type="lucas">t(ibi)</seg>
		       <orig>ṫ</orig>
		       <reg>tibi</reg>
	     </choice> 
	     <choice>
		       <seg type="lucas">d(omi)ne</seg>
		       <orig>dn̄e</orig>
		       <reg>domine</reg>
	     </choice> 
	     <choice>
		       <seg type="lucas">o(mn)ia</seg>
		       <orig>ōia</orig>
		       <reg>omnia</reg>
	     </choice>
      <lb/>
	     <choice>
		       <seg type="lucas">op(er)a</seg>
		       <orig>oꝑa</orig>
		       <reg>opera</reg>
	     </choice> tua: 
	<choice>
		       <seg type="lucas">(et) </seg>
		       <orig>+ </orig>
		       <reg>et </reg>
	     </choice> 
	     <choice>
		       <seg type="lucas">s(an)c(t)i</seg>
		       <orig>sc̄i</orig>
		       <reg>sancti</reg>
	     </choice> tui 
	<choice>
		       <seg type="lucas">b(e)n(e)dica(n)t</seg>
		       <orig>bn̄dic̄at</orig>
		       <reg>benedicant</reg>
	     </choice>
      <lb/>
	     <choice>
		       <seg type="lucas">t(ibi).</seg>
		       <orig>ṫ.</orig>
		       <reg>tibi.</reg>
	     </choice> 
	     <choice>
		       <seg type="lucas">Gl(ori)a(m)</seg>
		       <orig>Gl͘a⋮</orig>
		       <reg>Gloriam</reg>
	     </choice> 
	     <choice>
		       <seg type="lucas">reg(ni)</seg>
		       <orig>reġ</orig>
		       <reg>regni</reg>
	     </choice> tui 
	<choice>
		       <seg type="lucas">dice(n)t:</seg>
		       <orig>dicēt:</orig>
		       <reg>dicent:</reg>
	     </choice> et


</ab>

   <ab type="translation"
       xml:id="p0241_translation"
       corresp="#p0241_transcription"/>

</div>
