<?xml version="1.0" encoding="UTF-8"?>
<?xml-model href="../schema/out/dragon_schema.rng" type="application/xml" schematypens="http://relaxng.org/ns/structure/1.0"?>
<div xmlns="http://www.tei-c.org/ns/1.0"
     type="page"
     n="143r"
     xml:id="p0301">

   <ab type="transcription"
       xml:id="p0301_transcription"
       corresp="#p0301_translation">

      <lb/>ad me 
	<choice>
		       <seg type="lucas">decli(n)et</seg>
		       <orig>decliet</orig>
		       <reg>declinet</reg>
	     </choice> 
	     <choice>
		       <seg type="lucas">(et) </seg>
		       <orig> </orig>
		       <reg>et </reg>
	     </choice> 
	     <choice>
		       <seg type="lucas">ea(m)</seg>
		       <orig>ea</orig>
		       <reg>eam</reg>
	     </choice> 
	     <choice>
		       <seg type="lucas">i(n)veni</seg>
		       <orig>iveni</orig>
		       <reg>inveni</reg>
	     </choice>
      <lb break="no"/>et 
	<choice>
		       <seg type="lucas">(et) </seg>
		       <orig> </orig>
		       <reg>et </reg>
	     </choice> 
	     <choice>
		       <seg type="lucas">ea(m)</seg>
		       <orig>ea</orig>
		       <reg>eam</reg>
	     </choice> 
	     <choice>
		       <seg type="lucas">c(um)</seg>
		       <orig>c</orig>
		       <reg>cum</reg>
	     </choice> 
	     <choice>
		       <seg type="lucas">i(n)ven(er)it</seg>
		       <orig>ivenit</orig>
		       <reg>invenerit</reg>
	     </choice> 
	     <choice>
		       <seg type="lucas">b(ea)t(u)s</seg>
		       <orig>bts</orig>
		       <reg>beatus</reg>
	     </choice> erit
<lb/>si 
	<choice>
		       <seg type="lucas">detinu(er)it</seg>
		       <orig>detinuit</orig>
		       <reg>detinuerit</reg>
	     </choice> 
	     <choice>
		       <seg type="lucas">ea(m).</seg>
		       <orig>ea.</orig>
		       <reg>eam.</reg>
	     </choice> 
	     <choice>
		       <seg type="lucas">a(lleluia?).</seg>
		       <orig>a.</orig>
		       <reg>alleluia?.<!--  check expansion --></reg>
	     </choice> 
 
	     <choice>
		       <seg type="lucas">D(omi)n(us)</seg>
		       <orig>Dn</orig>
		       <reg>Dominus</reg>
	     </choice> pos
<lb break="no"/>sedit me 
	<choice>
		       <seg type="lucas">i(n)</seg>
		       <orig>i</orig>
		       <reg>in</reg>
	     </choice> 
	     <choice>
		       <seg type="lucas">i(n)it(i)o</seg>
		       <orig>iito</orig>
		       <reg>initio</reg>
	     </choice> 
	     <choice>
		       <seg type="lucas">viar(um)</seg>
		       <orig>viar</orig>
		       <reg>viarum</reg>
	     </choice> sua
<lb break="no"/>
	     <choice>
		       <seg type="lucas">r(um)</seg>
		       <orig>r</orig>
		       <reg>rum</reg>
	     </choice> 
	     <choice>
		       <seg type="lucas">an(te)q(uam)</seg>
		       <orig>anq</orig>
		       <reg>antequam</reg>
	     </choice> 
	     <choice>
		       <seg type="lucas">q(ui)cq(uam)</seg>
		       <orig>qcq</orig>
		       <reg>quicquam</reg>
	     </choice> 
	     <choice>
		       <seg type="lucas">face(re)t</seg>
		       <orig>facet</orig>
		       <reg>faceret</reg>
	     </choice> a 
	<choice>
		       <seg type="lucas">p(ri)nci</seg>
		       <orig>pnci</orig>
		       <reg>princi</reg>
	     </choice>
      <lb break="no"/>pio 
	<choice>
		       <seg type="lucas">necdu(m)</seg>
		       <orig>necdu</orig>
		       <reg>necdum</reg>
	     </choice> 
	     <choice>
		       <seg type="lucas">era(n)t</seg>
		       <orig>erat</orig>
		       <reg>erant</reg>
	     </choice> abyssi
<lb/>
	     <choice>
		       <seg type="lucas">(et) </seg>
		       <orig> </orig>
		       <reg>et </reg>
	     </choice> ego 
	<choice>
		       <seg type="lucas">p(ar)turiebar</seg>
		       <orig>pturiebar</orig>
		       <reg>parturiebar</reg>
	     </choice> 
	     <choice>
		       <seg type="lucas">qu(ando)</seg>
		       <orig>qu</orig>
		       <reg>quando</reg>
	     </choice> 
	     <choice>
		       <seg type="lucas">p(re)p(ar)a</seg>
		       <orig>ppa</orig>
		       <reg>prepara</reg>
	     </choice>
      <lb break="no"/>bat celos 
	<choice>
		       <seg type="lucas">adera(m)</seg>
		       <orig>adera</orig>
		       <reg>aderam</reg>
	     </choice> 
	     <choice>
		       <seg type="lucas">cu(m)</seg>
		       <orig>cu</orig>
		       <reg>cum</reg>
	     </choice> eo 
	<choice>
		       <seg type="lucas">co(m)</seg>
		       <orig>co</orig>
		       <reg>com</reg>
	     </choice>
      <lb break="no"/>
	     <choice>
		       <seg type="lucas">pone(n)s</seg>
		       <orig>pones</orig>
		       <reg>ponens</reg>
	     </choice> 
	     <choice>
		       <seg type="lucas">o(mn)ia.</seg>
		       <orig>oia.</orig>
		       <reg>omnia.</reg>
	     </choice> 
	     <choice>
		       <seg type="lucas">a(lleluia?).</seg>
		       <orig>a.</orig>
		       <reg>alleluia?.<!--  check expansion --></reg>
	     </choice> 
 Ego 
	<choice>
		       <seg type="lucas">i(n)</seg>
		       <orig>i</orig>
		       <reg>in</reg>
	     </choice> al
<lb break="no"/>
	     <choice>
		       <seg type="lucas">tissi(mi)s</seg>
		       <orig>tissis</orig>
		       <reg>tissimis</reg>
	     </choice> 
	     <choice>
		       <seg type="lucas">h(ab)itavi</seg>
		       <orig>hitavi</orig>
		       <reg>habitavi</reg>
	     </choice> 
	     <choice>
		       <seg type="lucas">(et) </seg>
		       <orig> </orig>
		       <reg>et </reg>
	     </choice> thronus
<lb/>
	     <choice>
		       <seg type="lucas">m(eu)s</seg>
		       <orig>ms</orig>
		       <reg>meus</reg>
	     </choice> 
	     <choice>
		       <seg type="lucas">i(n)</seg>
		       <orig>i</orig>
		       <reg>in</reg>
	     </choice> 
	     <choice>
		       <seg type="lucas">colu(m)na</seg>
		       <orig>coluna</orig>
		       <reg>columna</reg>
	     </choice> 
	     <choice>
		       <seg type="lucas">nub(is).</seg>
		       <orig>nub.</orig>
		       <reg>nubis.</reg>
	     </choice> 
	     <choice>
		       <seg type="lucas">Do(minica)</seg>
		       <orig>Do</orig>
		       <reg>Dominica</reg>
	     </choice>
      <lb/>
	     <choice>
		       <seg type="lucas">i(n)</seg>
		       <orig>i</orig>
		       <reg>in</reg>
	     </choice> 
	     <choice>
		       <seg type="lucas">septe(m)b(ri?)s.</seg>
		       <orig>septebs.</orig>
		       <reg>septembri?s.</reg>
	     </choice> 
	     <choice>
		       <seg type="lucas">R(esponsorium).</seg>
		       <orig>R.</orig>
		       <reg>Responsorium.</reg>
	     </choice> 
	     <choice>
		       <seg type="lucas">An(te)q(uam)</seg>
		       <orig>Anq</orig>
		       <reg>Antequam</reg>
	     </choice> co
<lb break="no"/>
	     <choice>
		       <seg type="lucas">meda(m)</seg>
		       <orig>meda</orig>
		       <reg>medam</reg>
	     </choice> suspiro 
	<choice>
		       <seg type="lucas">(et) </seg>
		       <orig> </orig>
		       <reg>et </reg>
	     </choice> 
	     <choice>
		       <seg type="lucas">ta(m)q(uam)</seg>
		       <orig>taq</orig>
		       <reg>tamquam</reg>
	     </choice> in
<lb break="no"/>
	     <choice>
		       <seg type="lucas">u(n)datis</seg>
		       <orig>udatis</orig>
		       <reg>undatis</reg>
	     </choice> 
	     <choice>
		       <seg type="lucas">aq(ue)</seg>
		       <orig>aq</orig>
		       <reg>aque</reg>
	     </choice> sic 
	<choice>
		       <seg type="lucas">rugit(us)</seg>
		       <orig>rugit</orig>
		       <reg>rugitus</reg>
	     </choice> 
	     <choice>
		       <seg type="lucas">m(eu)s</seg>
		       <orig>ms</orig>
		       <reg>meus</reg>
	     </choice>
      <lb/>
	     <choice>
		       <seg type="lucas">q(uia)</seg>
		       <orig>q</orig>
		       <reg>quia</reg>
	     </choice> 
	     <choice>
		       <seg type="lucas">ti(m)or</seg>
		       <orig>tior</orig>
		       <reg>timor</reg>
	     </choice> 
	     <choice>
		       <seg type="lucas">que(m)</seg>
		       <orig>que</orig>
		       <reg>quem</reg>
	     </choice> 
	     <choice>
		       <seg type="lucas">ti(m)eba(m)</seg>
		       <orig>tieba</orig>
		       <reg>timebam</reg>
	     </choice> evenit


</ab>

   <ab type="translation"
       xml:id="p0301_translation"
       corresp="#p0301_transcription"/>

</div>
