<?xml version="1.0" encoding="UTF-8"?>
<?xml-model href="../schema/out/dragon_schema.rng" type="application/xml" schematypens="http://relaxng.org/ns/structure/1.0"?>
<div xmlns="http://www.tei-c.org/ns/1.0"
     type="page"
     n="253v"
     xml:id="p0522">

   <ab type="transcription"
       xml:id="p0522_transcription"
       corresp="#p0522_translation">

      <lb/>illic erit 
	<choice>
		       <seg type="lucas">(et) </seg>
		       <orig> </orig>
		       <reg>et </reg>
	     </choice> 
	     <choice>
		       <seg type="lucas">mi(?)
	</seg>
		       <orig>mi
	</orig>
		       <reg>mi?
	<!--  check expansion --></reg>
	     </choice> 
      <choice>
		       <seg type="lucas">st(er)</seg>
		       <orig>st</orig>
		       <reg>ster</reg>
	     </choice> 
	     <choice>
		       <seg type="lucas">m(eu)s.</seg>
		       <orig>ms.</orig>
		       <reg>meus.</reg>
	     </choice> 
	     <choice>
		       <seg type="lucas">a(lleluia?).</seg>
		       <orig>a.</orig>
		       <reg>alleluia?.<!--  check expansion --></reg>
	     </choice> 
 Vo
<lb break="no"/>lo 
	<choice>
		       <seg type="lucas">p(ate)r</seg>
		       <orig>pr</orig>
		       <reg>pater</reg>
	     </choice> ut ubi ego 
	<choice>
		       <seg type="lucas">su(m)</seg>
		       <orig>su</orig>
		       <reg>sum</reg>
	     </choice> illic sit
<lb/>
	     <choice>
		       <seg type="lucas">(et) </seg>
		       <orig> </orig>
		       <reg>et </reg>
	     </choice> 
	     <choice>
		       <seg type="lucas">mi(?)
	</seg>
		       <orig>mi
	</orig>
		       <reg>mi?
	<!--  check expansion --></reg>
	     </choice> 
      <choice>
		       <seg type="lucas">st(er)</seg>
		       <orig>st</orig>
		       <reg>ster</reg>
	     </choice> 
	     <choice>
		       <seg type="lucas">m(eu)s.</seg>
		       <orig>ms.</orig>
		       <reg>meus.</reg>
	     </choice> 
	     <choice>
		       <seg type="lucas">Cap(ite)</seg>
		       <orig>Cap</orig>
		       <reg>Capite</reg>
	     </choice> 
	     <choice>
		       <seg type="lucas">B(ea)t(u)s.</seg>
		       <orig>Bts.</orig>
		       <reg>Beatus.</reg>
	     </choice> 
	     <choice>
		       <seg type="lucas">(h)</seg>
		       <orig/>
		       <reg>h</reg>
	     </choice>
	     <choice>
		       <seg type="lucas">y(m)n(us).</seg>
		       <orig>yn.</orig>
		       <reg>ymnus.</reg>
	     </choice>
      <lb/>MArtir dei 
	<choice>
		       <seg type="lucas">q(ui)</seg>
		       <orig>q</orig>
		       <reg>qui</reg>
	     </choice> 
	     <choice>
		       <seg type="lucas">vi(n)cu(m)</seg>
		       <orig>vicu</orig>
		       <reg>vincum</reg>
	     </choice> 
	     <choice>
		       <seg type="lucas">p(at)ris</seg>
		       <orig>pris</orig>
		       <reg>patris</reg>
	     </choice>
      <lb/>
	     <choice>
		       <seg type="lucas">seq(ue)ndo</seg>
		       <orig>seqndo</orig>
		       <reg>sequendo</reg>
	     </choice> 
	     <choice>
		       <seg type="lucas">filiu(m)</seg>
		       <orig>filiu</orig>
		       <reg>filium</reg>
	     </choice> victis 
	<choice>
		       <seg type="lucas">t(ri)</seg>
		       <orig>t</orig>
		       <reg>tri</reg>
	     </choice>
      <lb break="no"/>
	     <choice>
		       <seg type="lucas">u(m)pha(n)s</seg>
		       <orig>uphas</orig>
		       <reg>umphans</reg>
	     </choice> 
	     <choice>
		       <seg type="lucas">hostib(us)</seg>
		       <orig>hostib</orig>
		       <reg>hostibus</reg>
	     </choice> victor fru
<lb break="no"/>
	     <choice>
		       <seg type="lucas">e(n)s</seg>
		       <orig>es</orig>
		       <reg>ens</reg>
	     </choice> 
	     <choice>
		       <seg type="lucas">celestib(us).</seg>
		       <orig>celestib.</orig>
		       <reg>celestibus.</reg>
	     </choice> Tui 
	<choice>
		       <seg type="lucas">p(re)cat(us)</seg>
		       <orig>pcat</orig>
		       <reg>precatus</reg>
	     </choice> mu
<lb break="no"/>
	     <choice>
		       <seg type="lucas">ne(re)</seg>
		       <orig>ne</orig>
		       <reg>nere</reg>
	     </choice> 
	     <choice>
		       <seg type="lucas">n(ost)r(u)m</seg>
		       <orig>nrm</orig>
		       <reg>nostrum</reg>
	     </choice> 
	     <choice>
		       <seg type="lucas">reatu(m)</seg>
		       <orig>reatu</orig>
		       <reg>reatum</reg>
	     </choice> dilue 
	<choice>
		       <seg type="lucas">arre(n)s?</seg>
		       <orig>arres?</orig>
		       <reg>arrens?</reg>
	     </choice>
      <lb/>mali 
	<choice>
		       <seg type="lucas">(con)</seg>
		       <orig/>
		       <reg>con</reg>
	     </choice>
	     <choice>
		       <seg type="lucas">tagiu(m)</seg>
		       <orig>tagiu</orig>
		       <reg>tagium</reg>
	     </choice> vite 
	<choice>
		       <seg type="lucas">remone(n)s</seg>
		       <orig>remones</orig>
		       <reg>remonens</reg>
	     </choice>
      <lb/>
	     <choice>
		       <seg type="lucas">tediu(m).</seg>
		       <orig>tediu.</orig>
		       <reg>tedium.</reg>
	     </choice> Soluta 
	<choice>
		       <seg type="lucas">s(un)t</seg>
		       <orig>st</orig>
		       <reg>sunt</reg>
	     </choice> 
	     <choice>
		       <seg type="lucas">ia(m)</seg>
		       <orig>ia</orig>
		       <reg>iam</reg>
	     </choice> 
	     <choice>
		       <seg type="lucas">vi(n)c(u)la</seg>
		       <orig>vicla</orig>
		       <reg>vincula</reg>
	     </choice>
      <lb/>tui 
	<choice>
		       <seg type="lucas">sac(ra)ti</seg>
		       <orig>sacti</orig>
		       <reg>sacrati</reg>
	     </choice> 
	     <choice>
		       <seg type="lucas">corp(or)is</seg>
		       <orig>corpis</orig>
		       <reg>corporis</reg>
	     </choice> nos solve
<lb/>
	     <choice>
		       <seg type="lucas">vi(n)c(u?)lis</seg>
		       <orig>viclis</orig>
		       <reg>vincu?lis</reg>
	     </choice> 
	     <choice>
		       <seg type="lucas">s(e)c(u)li</seg>
		       <orig>scli</orig>
		       <reg>seculi</reg>
	     </choice> amore filii dei.
<lb/>Deo 
	<choice>
		       <seg type="lucas">p(at)risit</seg>
		       <orig>prisit</orig>
		       <reg>patrisit</reg>
	     </choice> 
	     <choice>
		       <seg type="lucas">gl(ori)a</seg>
		       <orig>gla</orig>
		       <reg>gloria</reg>
	     </choice> 
	     <choice>
		       <seg type="lucas">eiusq(ue)</seg>
		       <orig>eiusq</orig>
		       <reg>eiusque</reg>
	     </choice> s. f.
<lb/>
	     <choice>
		       <seg type="lucas">c(um)</seg>
		       <orig>c</orig>
		       <reg>cum</reg>
	     </choice> s. p. 
	<choice>
		       <seg type="lucas">(et) </seg>
		       <orig> </orig>
		       <reg>et </reg>
	     </choice> n. 
	<choice>
		       <seg type="lucas">(et) </seg>
		       <orig> </orig>
		       <reg>et </reg>
	     </choice> 
	     <choice>
		       <seg type="lucas">i(n)</seg>
		       <orig>i</orig>
		       <reg>in</reg>
	     </choice> 
	     <choice>
		       <seg type="lucas">p(er)petuu(m).</seg>
		       <orig>ppetuu.</orig>
		       <reg>perpetuum.</reg>
	     </choice> 
	     <choice>
		       <seg type="lucas">V(ersiculus).</seg>
		       <orig>V.</orig>
		       <reg>Versiculus.</reg>
	     </choice> Co
<lb break="no"/>
	     <choice>
		       <seg type="lucas">ro(na)</seg>
		       <orig>ro</orig>
		       <reg>rona</reg>
	     </choice> aurea 
	<choice>
		       <seg type="lucas">s(upe)r</seg>
		       <orig>sr</orig>
		       <reg>super</reg>
	     </choice> caput 
	<choice>
		       <seg type="lucas">ei(us).</seg>
		       <orig>ei.</orig>
		       <reg>eius.</reg>
	     </choice> 
	     <choice>
		       <seg type="lucas">Exp(re)s⸗</seg>
		       <orig>Exps⸗</orig>
		       <reg>Expres⸗</reg>
	     </choice>
   </ab>

   <ab type="translation"
       xml:id="p0522_translation"
       corresp="#p0522_transcription"/>

</div>
